plyse/__init__.py
plyse/grammar.py
plyse/parser.py
plyse/query.py
plyse/query_tree.py
plyse/term_parser.py
plyse/util.py
plyse/expressions/__init__.py
plyse/expressions/operators.py
plyse/expressions/primitives.py
plyse/expressions/terms.py
plyse/tests/__init__.py
plyse/tests/grammar_from_config_test.py
plyse/tests/grammar_test.py
plyse/tests/parser_test.py
plyse/tests/primitives_test.py
plyse/tests/query_test.py
plyse/tests/query_tree_test.py
plyse/tests/term_parser_test.py
plyse/tests/terms_test.py
plyse-1.0.3.dist-info/LICENSE
plyse-1.0.3.dist-info/METADATA
plyse-1.0.3.dist-info/WHEEL
plyse-1.0.3.dist-info/top_level.txt
plyse-1.0.3.dist-info/RECORD
