Metadata-Version: 2.1
Name: plyse
Version: 1.0.3
Summary: A fully extensible query parser inspired on the lucene and gmail sintax
Home-page: https://github.com/sebastiandev/plyse
Author: Sebastian Packmann
Author-email: devsebas@gmail.com
License: MIT
Keywords: search query parser lucene gmail syntax grammar
Platform: UNKNOWN
Classifier: Development Status :: 5 - Production/Stable
Classifier: Intended Audience :: Developers
Classifier: License :: OSI Approved :: MIT License
Classifier: Operating System :: OS Independent
Classifier: Programming Language :: Python
Classifier: Programming Language :: Python :: 2.6
Classifier: Programming Language :: Python :: 2.7
Classifier: Programming Language :: Python :: 3
Classifier: Programming Language :: Python :: 3.3
Classifier: Programming Language :: Python :: 3.4
Classifier: Programming Language :: Python :: 3.5
Classifier: Programming Language :: Python :: 3.6
Classifier: Programming Language :: Python :: 3.7
Requires-Python: >=2.6, !=3.0.*, !=3.1.*, !=3.2.*
Requires-Dist: pyparsing
